<step title="BackgroundTrace" date="2026-01-02T09:15:43.532" instance="b52a0e" url="/api/publish" method="POST" >
  <step title="Creating temporary deployment - FetchDeploymentManager" date="2026-01-02T09:15:43.682" /><!-- duration: 1ms -->
  <step title="Creating temporary deployment" date="2026-01-02T09:15:43.700" /><!-- duration: 82ms -->
  <step title="Performing fetch based deployment" date="2026-01-02T09:15:43.808" >
    <step title="Cleaning up temp folders from previous zip deployments and extracting pushed zip file /tmp/zipdeploy/447bbf9f-0be8-4fe8-90a7-2451e6742776.zip (0.02 MB) to /tmp/zipdeploy/extracted" date="2026-01-02T09:15:44.964" >
      <step title="ChmodRecursive Process exited with total time taken in ms: 94" date="2026-01-02T09:15:45.335" /><!-- duration: 3ms -->
    </step><!-- duration: 390ms -->
    <step title="Deployment timer started" date="2026-01-02T09:15:47.393" >
      <step title="DeploymentManager.Deploy(id:77bf5294-4e98-4f4f-a5b4-b12f736e07af)" date="2026-01-02T09:15:47.402" >
        <step title="Collecting changeset information" date="2026-01-02T09:15:47.472" /><!-- duration: 119ms -->
        <step title="Updating submodules" date="2026-01-02T09:15:47.594" /><!-- duration: 1119ms -->
        <step title="Determining deployment builder" date="2026-01-02T09:15:48.900" >
          <step title="Builder is OryxBuilder" date="2026-01-02T09:15:48.918" /><!-- duration: 10ms -->
        </step><!-- duration: 40ms -->
        <step title="PreDeployment: context.CleanOutputPath False" date="2026-01-02T09:15:49.018" >
          <step title="PreDeployment: context.OutputPath /home/site/wwwroot" date="2026-01-02T09:15:49.116" >
            <step title="Building" date="2026-01-02T09:15:49.239" >
              <step title="Executing external process" date="2026-01-02T09:15:49.602" type="process" path="bash" arguments="-c &quot;oryx build /tmp/zipdeploy/extracted -o /home/site/wwwroot --platform python --platform-version 3.12 -p virtualenv_name=antenv --log-file /tmp/build-debug.log  -i /tmp/8de49df84e8ecf2 --compress-destination-dir | tee /tmp/oryx-build.log ; exit $PIPESTATUS &quot;" >
                <step title="Cpu: python(10041,3.550s)+python(10022,38.990s)+ts(10023,0.170s)+build.sh(10020,0.000s)+build.sh(10019,0.000s)+build.sh(9937,0.080s)+oryx(9919,3.630s)+tee(9920,0.000s)+bash(9918,0.000s)=total(46.400s)" date="2026-01-02T09:17:13.268" /><!-- duration: 37ms -->
                <step title="bash: no io activity for 61s, prev-cpu=-1.000s, current-cpu=46.400s" date="2026-01-02T09:17:13.437" /><!-- duration: 70ms -->
                <step title="Cpu: python(10022,52.160s)+ts(10023,0.260s)+build.sh(10020,0.000s)+build.sh(10019,0.000s)+build.sh(9937,0.080s)+oryx(9919,3.910s)+tee(9920,0.000s)+bash(9918,0.000s)=total(56.410s)" date="2026-01-02T09:18:14.237" /><!-- duration: 22ms -->
                <step title="bash: no io activity for 122s, prev-cpu=46.400s, current-cpu=56.410s" date="2026-01-02T09:18:14.468" /><!-- duration: 9ms -->
                <step title="Cpu: cc1(10074,24.710s)+gcc(10071,0.010s)+python(10070,0.910s)+python(10022,52.220s)+ts(10023,0.260s)+build.sh(10020,0.000s)+build.sh(10019,0.000s)+build.sh(9937,0.080s)+oryx(9919,4.010s)+tee(9920,0.000s)+bash(9918,0.000s)=total(82.200s)" date="2026-01-02T09:19:15.182" /><!-- duration: 20ms -->
                <step title="bash: no io activity for 183s, prev-cpu=56.410s, current-cpu=82.200s" date="2026-01-02T09:19:15.233" /><!-- duration: 29ms -->
                <step title="Cpu: python(10022,69.380s)+ts(10023,0.260s)+build.sh(10020,0.000s)+build.sh(10019,0.000s)+build.sh(9937,0.080s)+oryx(9919,4.110s)+tee(9920,0.000s)+bash(9918,0.000s)=total(73.830s)" date="2026-01-02T09:20:15.581" /><!-- duration: 10ms -->
                <step title="bash: no io activity for 243s, prev-cpu=82.200s, current-cpu=73.830s" date="2026-01-02T09:20:15.629" /><!-- duration: 26ms -->
                <step title="Cpu: python(10022,114.060s)+ts(10023,0.260s)+build.sh(10020,0.000s)+build.sh(10019,0.000s)+build.sh(9937,0.080s)+oryx(9919,4.190s)+tee(9920,0.000s)+bash(9918,0.000s)=total(118.590s)" date="2026-01-02T09:21:15.885" /><!-- duration: 12ms -->
                <step title="bash: no io activity for 303s, prev-cpu=73.830s, current-cpu=118.590s" date="2026-01-02T09:21:15.953" /><!-- duration: 52ms -->
                <step title="Cpu: python(10022,156.070s)+ts(10023,0.260s)+build.sh(10020,0.000s)+build.sh(10019,0.000s)+build.sh(9937,0.080s)+oryx(9919,4.220s)+tee(9920,0.000s)+bash(9918,0.000s)=total(160.630s)" date="2026-01-02T09:22:16.355" /><!-- duration: 40ms -->
                <step title="bash: no io activity for 364s, prev-cpu=118.590s, current-cpu=160.630s" date="2026-01-02T09:22:16.413" /><!-- duration: 19ms -->
                <step title="Cpu: python(10022,180.110s)+ts(10023,0.260s)+build.sh(10020,0.000s)+build.sh(10019,0.000s)+build.sh(9937,0.080s)+oryx(9919,4.290s)+tee(9920,0.000s)+bash(9918,0.000s)=total(184.740s)" date="2026-01-02T09:23:17.074" /><!-- duration: 51ms -->
                <step title="bash: no io activity for 425s, prev-cpu=160.630s, current-cpu=184.740s" date="2026-01-02T09:23:17.215" /><!-- duration: 38ms -->
                <step title="Cpu: gzip(10241,38.080s)+sh(10240,0.010s)+tar(10239,3.030s)+build.sh(9937,0.090s)+oryx(9919,4.900s)+tee(9920,0.000s)+bash(9918,0.000s)=total(46.110s)" date="2026-01-02T09:26:00.254" /><!-- duration: 3ms -->
                <step title="bash: no io activity for 60s, prev-cpu=-1.000s, current-cpu=46.110s" date="2026-01-02T09:26:00.275" /><!-- duration: 21ms -->
                <step title="Cpu: gzip(10241,77.130s)+sh(10240,0.010s)+tar(10239,5.610s)+build.sh(9937,0.090s)+oryx(9919,4.920s)+tee(9920,0.000s)+bash(9918,0.000s)=total(87.760s)" date="2026-01-02T09:27:00.594" /><!-- duration: 10ms -->
                <step title="bash: no io activity for 121s, prev-cpu=46.110s, current-cpu=87.760s" date="2026-01-02T09:27:00.643" /><!-- duration: 36ms -->
                <step title="Cpu: gzip(10241,93.960s)+sh(10240,0.010s)+tar(10239,8.030s)+build.sh(9937,0.090s)+oryx(9919,4.920s)+tee(9920,0.000s)+bash(9918,0.000s)=total(107.010s)" date="2026-01-02T09:28:01.769" /><!-- duration: 145ms -->
                <step title="bash: no io activity for 182s, prev-cpu=87.760s, current-cpu=107.010s" date="2026-01-02T09:28:02.020" /><!-- duration: 59ms -->
                <step title="Cpu: gzip(10241,106.190s)+sh(10240,0.010s)+tar(10239,9.360s)+build.sh(9937,0.090s)+oryx(9919,4.950s)+tee(9920,0.000s)+bash(9918,0.000s)=total(120.600s)" date="2026-01-02T09:29:02.986" /><!-- duration: 80ms -->
                <step title="bash: no io activity for 243s, prev-cpu=107.010s, current-cpu=120.600s" date="2026-01-02T09:29:03.168" /><!-- duration: 89ms -->
              </step><!-- duration: 836447ms -->
              <step title="Using PythonDeploymentLogParser" date="2026-01-02T09:29:46.916" /><!-- duration: 4ms -->
              <step title="Modified file to trigger a restart of the app container." date="2026-01-02T09:29:48.604" /><!-- duration: 10ms -->
              <step title="Skip function trigger and logicapp sync because function is not enabled." date="2026-01-02T09:29:48.622" /><!-- duration: 18ms -->
              <step title="Purge deployment items" date="2026-01-02T09:29:49.997" >
                <step title="Remove 4e577997-, Success, received at 01/02/2026 01:53:59" date="2026-01-02T09:29:50.274" /><!-- duration: 29ms -->
              </step><!-- duration: 328ms -->
            </step><!-- duration: 841214ms -->
          </step><!-- duration: 841348ms -->
          <step title="Cleaning up temp files" date="2026-01-02T09:29:50.472" /><!-- duration: 6581ms -->
          <step title="Cleaning up temp files" date="2026-01-02T09:29:57.057" /><!-- duration: 525ms -->
          <step title="Reloading status file with latest updates" date="2026-01-02T09:29:57.598" >
            <step title="WebHooksManager.PublishEventAsync: PostDeployment" date="2026-01-02T09:29:57.601" /><!-- duration: 79ms -->
          </step><!-- duration: 83ms -->
          <step title="Cleaning up temporary deployment - fetch deployment was successful" date="2026-01-02T09:29:57.687" /><!-- duration: 3ms -->
        </step><!-- duration: 848728ms -->
      </step><!-- duration: 850356ms -->
