<step title="Incoming Request" date="2026-01-02T13:48:06.322" instance="b52a0e" url="/api/deployments/latest?deployer=OneDeploy&amp;time=2026-01-02_13-43-18Z" method="GET" type="request" pid="767,1,28" Host="abaco-analytics-dashboard-gbbjege0gxcbhyg9.scm.canadacentral-01.azurewebsites.net" User-Agent="GITHUBACTIONS_DeployWebAppToAzure_b331d4c441121f33da0f8476235474cf2ed43174776f44c9c3bb512e436c79b1" Authorization="Bea..." Content-Type="application/json; charset=utf-8" Cookie="ARRAffinity=b52a0e95239a69ec1d51e27f609b0a5686f7c63777a6973635d661be711de39f;Path=/;HttpOnly;Secure;Domain=abaco-analytics-dashboard-gbbjege0gxcbhyg9.scm.canadacentral-01.azurewebsites.net; ARRAffinitySameSite=b52a0e95239a69ec1d51e27f609b0a5686f7c63777a6973635d661be711de39f;Path=/;HttpOnly;SameSite=None;Secure;Domain=abaco-analytics-dashboard-gbbjege0gxcbhyg9.scm.canadacentral-01.azurewebsites.net" Content-Length="0" X-ARR-LOG-ID="81be6e28-4f10-4f57-96e2-b2afb198e524" CLIENT-IP="40.76.119.212:61464" X-SITE-DEPLOYMENT-ID="abaco-analytics-dashboard" WAS-DEFAULT-HOSTNAME="abaco-analytics-dashboard-gbbjege0gxcbhyg9.scm.canadacentral-01.azurewebsites.net" X-Forwarded-Proto="https" X-AppService-Proto="https" X-Forwarded-TlsVersion="1.3" X-WAWS-Unencoded-URL="/api/deployments/latest?deployer=OneDeploy&amp;time=2026-01-02_13-43-18Z" X-Client-IP="40.76.119.212" X-Client-Port="61464" >
  <step title="Cleanup Xml Logs" date="2026-01-02T13:48:06.325" >
    <step title="Cleanup Infos" date="2026-01-02T13:48:06.932" totalFiles="3789" totalCleanup="3629" /><!-- duration: 109ms -->
  </step><!-- duration: 748ms -->
  <step title="DeploymentService.GetResult" date="2026-01-02T13:48:07.202" >
    <step title="DeploymentService.GetLatestDeployment" date="2026-01-02T13:48:07.213" >
      <step title="DeploymentManager.GetResults" date="2026-01-02T13:48:07.243" /><!-- duration: 1801ms -->
    </step><!-- duration: 1942ms -->
  </step><!-- duration: 2004ms -->
  <step title="Outgoing response" date="2026-01-02T13:48:09.226" type="response" statusCode="202" statusText="Accepted" /><!-- duration: 150ms -->
</step><!-- duration: 3075ms -->
